{
    "metadata": {
        "branch": "conflicts_batch_six_jj",
        "commit": "c5db04d40f77ace29d30a19d033a40030f4b2a8e",
        "date_time": "2019-04-18 16:40:00",
        "remote": "ssh://git@github.com/ModelSEED/ModelSEEDDatabase",
        "user": "Sam_Seaver"
    },
    "method": "disambiguation",
    "reactions": [
        {
            "ecs": {
                "2.3.1.122": "true",
                "EC-2.3.1.122": "true"
            },
            "from": {
                "def": "(2) alpha,alpha'-Trehalose 6-mycolate[0] <=> (1) TRHL[0] + (1) alpha,alpha'-Trehalose 6,6'-bismycolate[0]",
                "id": "rxn05015"
            },
            "names": {
                "6'-mycolyltransferase": "true",
                "alpha,alpha'-trehalose 6-monomycolate:alpha,alpha'-trehalose mycolyltransferase": "true",
                "alpha,alpha'-trehalose-6-mycolate:alpha,alpha'-trehalose-6-mycolate": "true",
                "alpha,alpha'-trehalose-6-mycolate:alpha,alpha'-trehalose-6-mycolate 6'-mycolyltransferase": "true",
                "alpha,alpha-trehalose-6-mycolate:alpha,alpha-trehalose-6-mycolate 6'-mycolyltransferase": "true",
                "trehalose O-mycolyltransferase": "true"
            },
            "to": {
                "def": "(2) CPD1G-1344[0] <=> (1) TRHL[0] + (1) alpha,alpha'-Trehalose 6,6'-bismycolate[0]",
                "id": "rxn48575"
            }
        }
    ]
}